setup.py
language_middleware/__init__.py
language_middleware.egg-info/PKG-INFO
language_middleware.egg-info/SOURCES.txt
language_middleware.egg-info/dependency_links.txt
language_middleware.egg-info/entry_points.txt
language_middleware.egg-info/not-zip-safe
language_middleware.egg-info/pbr.json
language_middleware.egg-info/top_level.txt