Metadata-Version: 1.1
Name: language-middleware
Version: 0.6
Summary: This Wsgi middleware, takes the language from urls similiar to '/es/documents' or from the Accept language header.
Home-page: https://github.com/dperezrada/wsgi-language-middleware
Author: Daniel Perez Rada
Author-email: dperezrada at gmail
License: GNU Public License v3.0
Keywords: wsgi middleware language i18n translation
Platform: UNKNOWN
Classifier: Development Status :: 4 - Beta
Classifier: Topic :: Internet :: WWW/HTTP :: WSGI :: Middleware
Classifier: Intended Audience :: Developers
Classifier: License :: OSI Approved :: GNU General Public License (GPL)
